README.md
setup.cfg
setup.py
py_mgr/__init__.py
py_mgr/core.py
py_mgr.egg-info/PKG-INFO
py_mgr.egg-info/SOURCES.txt
py_mgr.egg-info/dependency_links.txt
py_mgr.egg-info/top_level.txt