Metadata-Version: 2.1
Name: py-mgr
Version: 0.0.9
Summary: administration of modules and plugin
Home-page: https://github.com/FlavioLionelRita/py-mgr
Author: Flavio Lionel Rita
Author-email: flaviolrita@hotmail.com
License: UNKNOWN
Download-URL: https://github.com/FlavioLionelRita/py-mgr/tarball/0.0.9
Keywords: manager,plugin
Platform: UNKNOWN
